pytunegen/__init__.py
pytunegen/constants.py
pytunegen/midigen.py
pytunegen/tunegen.py
pytunegen-1.1.1.dist-info/LICENSE
pytunegen-1.1.1.dist-info/METADATA
pytunegen-1.1.1.dist-info/WHEEL
pytunegen-1.1.1.dist-info/top_level.txt
pytunegen-1.1.1.dist-info/RECORD
