Metadata-Version: 2.1
Name: pytunegen
Version: 1.1.1
Summary: Generates randomized music tunes with Python, with MIDI export support.
Home-page: https://github.com/arda-guler/pyTuneGen
Author: arda-guler
Author-email: ardaguler09@gmail.com
License: UNKNOWN
Project-URL: Bug Tracker, https://github.com/arda-guler/pyTuneGen/issues
Project-URL: Documentation, https://arda-guler.github.io/pytunegenDocs/index.html
Platform: UNKNOWN
Classifier: Programming Language :: Python :: 3
Classifier: License :: OSI Approved :: MIT License
Classifier: Operating System :: OS Independent
Requires-Python: >=3.6
License-File: LICENSE
Requires-Dist: midiutil
